{
  "title": "車内",
  "id": "ee6142b1-deca-4b51-805d-487ac47df407",
  "last_edited_time": "2023-05-25T12:20:00.000Z",
  "path": [
    "29 - Twittering Birds Never Fly"
  ],
  "blocks": [
    {
      "type": "paragraph",
      "id": "7d72d17a-b12e-4fcc-9bec-aa5de038575b",
      "paragraph": {
        "rich_text": [
          {
            "type": "text",
            "text": {
              "content": "WIP",
              "link": null
            },
            "annotations": {
              "bold": false,
              "italic": false,
              "strikethrough": false,
              "underline": false,
              "code": false,
              "color": "default"
            },
            "plain_text": "WIP",
            "href": null
          }
        ],
        "color": "default"
      }
    }
  ]
}